s3bids/__init__.py
s3bids/_version.py
s3bids/utils.py
s3bids/tests/test_s3bids.py
s3bids-0.1.7.dist-info/METADATA
s3bids-0.1.7.dist-info/WHEEL
s3bids-0.1.7.dist-info/licenses/LICENSE
s3bids-0.1.7.dist-info/RECORD
