Metadata-Version: 2.1
Name: s3bids
Version: 0.1.7
Summary: Useful classes for downloading BIDS datasets from S3.
Project-URL: Homepage, https://github.com/36000/s3bids
Author: NRDG
License: BSD3
License-File: LICENSE
Classifier: Programming Language :: Python :: 3
Classifier: Programming Language :: Python :: 3.8
Classifier: Programming Language :: Python :: 3.9
Classifier: Programming Language :: Python :: 3.10
Classifier: Programming Language :: Python :: 3.11
Requires-Python: >=3.8
